azure_uploader.py
PyUpdater_Azure_Blob_Plugin-0.1.0.dist-info/LICENCE
PyUpdater_Azure_Blob_Plugin-0.1.0.dist-info/METADATA
PyUpdater_Azure_Blob_Plugin-0.1.0.dist-info/WHEEL
PyUpdater_Azure_Blob_Plugin-0.1.0.dist-info/entry_points.txt
PyUpdater_Azure_Blob_Plugin-0.1.0.dist-info/top_level.txt
PyUpdater_Azure_Blob_Plugin-0.1.0.dist-info/RECORD
